androidmparser/__init__.py
androidmparser/adb_utils.py
androidmparser/config_manager.py
androidmparser/deeplink_generator.py
androidmparser/gui.py
androidmparser/history_manager.py
androidmparser/main.py
androidmparser/parser.py
androidmparser/paths.py
androidmparser/payload_manager.py
androidmparser/payloads_default.json
androidmparser/theme.py
androidmparser-1.0.3.dist-info/licenses/LICENSE
androidmparser-1.0.3.dist-info/METADATA
androidmparser-1.0.3.dist-info/WHEEL
androidmparser-1.0.3.dist-info/entry_points.txt
androidmparser-1.0.3.dist-info/top_level.txt
androidmparser-1.0.3.dist-info/RECORD
