Metadata-Version: 2.4
Name: androidmparser
Version: 1.0.3
Summary: Android manifest parser tool
Author-email: SevVet <sevvetapps@gmail.com>
License: MIT
Classifier: Programming Language :: Python :: 3
Classifier: License :: OSI Approved :: MIT License
Requires-Python: >=3.8
License-File: LICENSE
Requires-Dist: platformdirs
Dynamic: license-file
